pretix_gpwebpay/__init__.py
pretix_gpwebpay/apps.py
pretix_gpwebpay/payment.py
pretix_gpwebpay/pretix_plugin_urls.py
pretix_gpwebpay/signals.py
pretix_gpwebpay/tasks.py
pretix_gpwebpay/urls.py
pretix_gpwebpay/views.py
pretix_gpwebpay/locale/en/LC_MESSAGES/django.po
pretix_gpwebpay/static/pretix_gpwebpay/redirect.js
pretix_gpwebpay-6.0.29.dist-info/METADATA
pretix_gpwebpay-6.0.29.dist-info/WHEEL
pretix_gpwebpay-6.0.29.dist-info/entry_points.txt
pretix_gpwebpay-6.0.29.dist-info/top_level.txt
pretix_gpwebpay-6.0.29.dist-info/RECORD
