Metadata-Version: 2.1
Name: pretix-gpwebpay
Version: 6.0.29
Summary: GPWebPay payment provider for Pretix
Author-email: KrisIsNew <gpwebpay.pretix@krisisnew.xyz>
Maintainer-email: KrisIsNew <gpwebpay.pretix@krisisnew.xyz>
License: Apache-2.0
Project-URL: homepage, https://github.com/krisisnewxyz/pretix-gpwebpay
Project-URL: repository, https://github.com/krisisnewxyz/pretix-gpwebpay
Project-URL: documentation, https://github.com/krisisnewxyz/pretix-gpwebpay
Project-URL: issues, https://github.com/krisisnewxyz/pretix-gpwebpay/issues
Keywords: pretix,payment,gpwebpay
Classifier: License :: OSI Approved :: Apache Software License
Classifier: Development Status :: 4 - Beta
Classifier: Intended Audience :: Developers
Classifier: Programming Language :: Python :: 3
Classifier: Programming Language :: Python :: 3.8
Classifier: Programming Language :: Python :: 3.9
Classifier: Programming Language :: Python :: 3.10
Classifier: Programming Language :: Python :: 3.11
Classifier: Programming Language :: Python :: 3.12
Requires-Python: >=3.8
Requires-Dist: cryptography >=3.0.0
Requires-Dist: pretix >=2.7.0
